fmappy/__init__.py
fmappy/functor.py
fmappy-0.1.1.dist-info/LICENSE
fmappy-0.1.1.dist-info/WHEEL
fmappy-0.1.1.dist-info/METADATA
fmappy-0.1.1.dist-info/RECORD
