Metadata-Version: 2.1
Name: fmappy
Version: 0.1.1
Summary: Functor for Python, with a Pythonic UX
Home-page: https://github.com/xtofl/fmappy
License: MIT
Author: xtofl
Author-email: kristoffel.pirard@gmail.com
Requires-Python: >=3.8,<4.0
Classifier: Development Status :: 3 - Alpha
Classifier: Intended Audience :: Developers
Classifier: License :: OSI Approved :: MIT License
Classifier: Programming Language :: Python :: 3
Classifier: Programming Language :: Python :: 3.10
Classifier: Programming Language :: Python :: 3.8
Classifier: Programming Language :: Python :: 3.9
Classifier: Topic :: Software Development :: Libraries :: Python Modules
Project-URL: Documentation, https://github.com/xtofl/fmappy
Project-URL: Repository, https://github.com/xtofl/fmappy
